pbirest/__init__.py
pbirest/core.py
pbirest-0.0.6.dist-info/LICENSE.md
pbirest-0.0.6.dist-info/METADATA
pbirest-0.0.6.dist-info/WHEEL
pbirest-0.0.6.dist-info/top_level.txt
pbirest-0.0.6.dist-info/RECORD
