Metadata-Version: 2.1
Name: pbirest
Version: 0.0.6
Summary: A Python library created to easily use the Power BI REST API with Python
Home-page: https://github.com/AntoineDW/powerbi-rest-api-python
Author: Antoine DE WILDE
Author-email: antoinedewilde7@gmail.com
License: MIT
Keywords: power bi,powerbi,rest,api,rest api
Platform: UNKNOWN
Classifier: Development Status :: 3 - Alpha
Classifier: Intended Audience :: Developers
Classifier: Topic :: Software Development :: Libraries :: Python Modules
Classifier: License :: OSI Approved :: MIT License
Classifier: Programming Language :: Python :: 3
Classifier: Programming Language :: Python :: 3.4
Classifier: Programming Language :: Python :: 3.5
Classifier: Programming Language :: Python :: 3.6
Requires-Dist: requests
